gdzru/__about__.py
gdzru/__init__.py
gdzru/api.py
gdzru/exceptions.py
gdzru/types/__init__.py
gdzru/types/book.py
gdzru/types/full_book_list.py
gdzru/types/task.py
gdzru/types/type.py
gdzru-1.0.0.dist-info/METADATA
gdzru-1.0.0.dist-info/WHEEL
gdzru-1.0.0.dist-info/licenses/LICENSE.txt
gdzru-1.0.0.dist-info/RECORD
