Metadata-Version: 2.1
Name: gdzru
Version: 1.0.0
Summary: Python library for using gdz.ru API
Project-URL: Usage, https://github.com/Den4ikSuperOstryyPer4ik/GDZ-py#usage
Project-URL: Issues, https://github.com/Den4ikSuperOstryyPer4ik/GDZ-py/issues
Project-URL: Source, https://github.com/Den4ikSuperOstryyPer4ik/GDZ-py
Project-URL: Author, https://github.com/Den4ikSuperOstryyPer4ik
Author-email: Den4ikSuperOstryyPer4ik <oleynik.denis.2009@gmail.com>
License-Expression: MIT
License-File: LICENSE.txt
Keywords: api,gdz,gdz ru api,gdz.ru,gdz.ru api,gdzru,ru,гдз,гдз api,гдз ру
Classifier: License :: OSI Approved :: MIT License
Classifier: Programming Language :: Python
Classifier: Programming Language :: Python :: 3.9
Classifier: Programming Language :: Python :: 3.10
Classifier: Programming Language :: Python :: 3.11
Classifier: Programming Language :: Python :: Implementation :: CPython
Classifier: Programming Language :: Python :: Implementation :: PyPy
Requires-Python: >=3.9
Requires-Dist: aiohttp
Requires-Dist: pydantic
